curator/__init__.py
curator/_version.py
curator/actions.py
curator/config_utils.py
curator/exceptions.py
curator/indexlist.py
curator/logtools.py
curator/snapshotlist.py
curator/utils.py
curator/defaults/__init__.py
curator/defaults/client_defaults.py
curator/defaults/filter_elements.py
curator/defaults/filtertypes.py
curator/defaults/option_defaults.py
curator/defaults/settings.py
curator/validators/__init__.py
curator/validators/actions.py
curator/validators/config_file.py
curator/validators/filters.py
curator/validators/options.py
curator/validators/schemacheck.py
elasticsearch_curator_api-5.8.3.dist-info/LICENSE.txt
elasticsearch_curator_api-5.8.3.dist-info/METADATA
elasticsearch_curator_api-5.8.3.dist-info/NOTICE
elasticsearch_curator_api-5.8.3.dist-info/WHEEL
elasticsearch_curator_api-5.8.3.dist-info/top_level.txt
elasticsearch_curator_api-5.8.3.dist-info/RECORD
