Metadata-Version: 2.1
Name: elasticsearch-curator-api
Version: 5.8.3
Summary: Tending your Elasticsearch indices
Home-page: https://github.com/PerchSecurity/curator-api
Author: Elastic
Author-email: info@elastic.co
License: Apache License, Version 2.0
Keywords: elasticsearch time-series indexed index-expiry
Platform: UNKNOWN
Classifier: Intended Audience :: Developers
Classifier: Intended Audience :: System Administrators
Classifier: License :: OSI Approved :: Apache Software License
Classifier: Operating System :: OS Independent
Classifier: Programming Language :: Python
Classifier: Programming Language :: Python :: 2.7
Classifier: Programming Language :: Python :: 3.5
Classifier: Programming Language :: Python :: 3.6
Classifier: Programming Language :: Python :: 3.7
Requires-Dist: elasticsearch (<8.0.0,>=7.0.4)
Requires-Dist: urllib3 (<1.25,>=1.24.2)
Requires-Dist: requests (>=2.20.0)
Requires-Dist: boto3 (>=1.9.142)
Requires-Dist: requests-aws4auth (>=0.9)
Requires-Dist: pyyaml (>=3.13)
Requires-Dist: voluptuous (>=0.9.3)
Requires-Dist: certifi (>=2019.9.11)
Requires-Dist: six (>=1.11.0)
